popobot.py
popobot-0.4.dist-info/METADATA
popobot-0.4.dist-info/WHEEL
popobot-0.4.dist-info/top_level.txt
popobot-0.4.dist-info/RECORD
