Metadata-Version: 2.1
Name: popobot
Version: 0.4
Summary: 泡泡aiM机器人库
Home-page: https://github.com/HydroGest/PoPoBot
Author: HydroGest
Author-email: me@mkc.icu
License: MIT
Classifier: Topic :: Games/Entertainment 
Classifier: Topic :: Games/Entertainment :: Puzzle Games
Classifier: Topic :: Games/Entertainment :: Board Games
Classifier: Topic :: Software Development :: Libraries :: Python Modules
Classifier: Programming Language :: Python
Classifier: Programming Language :: Python :: 3
Classifier: Programming Language :: Python :: 3.5
Classifier: Programming Language :: Python :: 3.5
Classifier: Programming Language :: Python :: 3.6
Classifier: Programming Language :: Python :: 3.7
Classifier: Programming Language :: Python :: Implementation :: CPython
Requires-Dist: requests (<=2.29.0)
